nonebot_plugin_picstatus/__init__.py
nonebot_plugin_picstatus/__main__.py
nonebot_plugin_picstatus/bg_provider.py
nonebot_plugin_picstatus/config.py
nonebot_plugin_picstatus/misc_statistics.py
nonebot_plugin_picstatus/util.py
nonebot_plugin_picstatus/collectors/__init__.py
nonebot_plugin_picstatus/collectors/bot.py
nonebot_plugin_picstatus/collectors/cpu.py
nonebot_plugin_picstatus/collectors/disk.py
nonebot_plugin_picstatus/collectors/mem.py
nonebot_plugin_picstatus/collectors/misc.py
nonebot_plugin_picstatus/collectors/network.py
nonebot_plugin_picstatus/collectors/process.py
nonebot_plugin_picstatus/res/assets/default_avatar.webp
nonebot_plugin_picstatus/res/assets/default_bg.webp
nonebot_plugin_picstatus/res/js/globalThis.d.ts
nonebot_plugin_picstatus/res/js/init-global.js
nonebot_plugin_picstatus/res/js/lazy-load.js
nonebot_plugin_picstatus/res/js/load-plugin.js
nonebot_plugin_picstatus/templates/__init__.py
nonebot_plugin_picstatus/templates/pw_render.py
nonebot_plugin_picstatus/templates/default/__init__.py
nonebot_plugin_picstatus/templates/default/res/css/index.css
nonebot_plugin_picstatus/templates/default/res/css/no-blur.css
nonebot_plugin_picstatus/templates/default/res/css/no-radius.css
nonebot_plugin_picstatus/templates/default/res/css/no-shadow.css
nonebot_plugin_picstatus/templates/default/res/css/theme-dark.css
nonebot_plugin_picstatus/templates/default/res/templates/index.html.jinja
nonebot_plugin_picstatus/templates/default/res/templates/macros.html.jinja
nonebot_plugin_picstatus-2.2.1.post2.dist-info/METADATA
nonebot_plugin_picstatus-2.2.1.post2.dist-info/WHEEL
nonebot_plugin_picstatus-2.2.1.post2.dist-info/licenses/LICENSE
nonebot_plugin_picstatus-2.2.1.post2.dist-info/RECORD
