Metadata-Version: 2.4
Name: nonebot-plugin-picstatus
Version: 2.2.1.post2
Summary: A NoneBot2 plugin generates a picture which shows the status of current device
Project-URL: homepage, https://github.com/lgc-NB2Dev/nonebot-plugin-picstatus
Author-email: LgCookie <lgc2333@126.com>
License: MIT
License-File: LICENSE
Requires-Python: <4.0,>=3.10
Requires-Dist: anyio>=4.10.0
Requires-Dist: cookit[jinja,loguru,nonebot-localstore,playwright,pydantic]>=0.13.2
Requires-Dist: httpx>=0.28.1
Requires-Dist: jinja2>=3.1.6
Requires-Dist: nonebot-plugin-alconna>=0.59.4
Requires-Dist: nonebot-plugin-apscheduler>=0.5.0
Requires-Dist: nonebot-plugin-htmlrender>=0.6.6
Requires-Dist: nonebot-plugin-localstore>=0.7.4
Requires-Dist: nonebot-plugin-uninfo>=0.9.0
Requires-Dist: nonebot2>=2.4.3
Requires-Dist: psutil>=7.0.0
Requires-Dist: py-cpuinfo>=9.0.0
Requires-Dist: taskgroup>=0.2.2; python_version < '3.11'
Requires-Dist: yarl>=1.20.1
